MANIFEST.in
README.md
setup.py
bin/coolsignup
coolsignup/__init__.py
coolsignup/api.py
coolsignup/app.py
coolsignup/command_line_args.py
coolsignup/conf.py
coolsignup/email_account.py
coolsignup/emails.py
coolsignup/new_password_validator.py
coolsignup/signing.py
coolsignup/translator.py
coolsignup/url_add_element.py
coolsignup.egg-info/PKG-INFO
coolsignup.egg-info/SOURCES.txt
coolsignup.egg-info/dependency_links.txt
coolsignup.egg-info/requires.txt
coolsignup.egg-info/top_level.txt
coolsignup/locale/coolsignup.pot
coolsignup/locale/fr/LC_MESSAGES/coolsignup.mo
coolsignup/locale/fr/LC_MESSAGES/coolsignup.po